pyopl.cpython-38-x86_64-linux-gnu.so
PyOPL-2.0.dist-info/WHEEL
PyOPL-2.0.dist-info/METADATA
PyOPL-2.0.dist-info/COPYING
PyOPL-2.0.dist-info/top_level.txt
PyOPL-2.0.dist-info/RECORD
PyOPL.libs/libgcc_s-a04fdf82.so.1
PyOPL.libs/libstdc++-a9383cce.so.6.0.28
