Metadata-Version: 2.1
Name: PyOPL
Version: 2.0
Summary: OPL2/3 Adlib emulation
Author-email: Adam Nielsen <malvineous@shikadi.net>, Adam Biser <adambiser@gmail.com>
Maintainer-email: Laurence Dougal Myers <laurencedougalmyers@gmail.com>
License: GPL-3.0-only
Project-URL: Repository, http://www.github.com/Malvineous/pyopl
Keywords: Adlib,FM,OPL,OPL2,OPL3,YM3812,YMF262
Classifier: Development Status :: 5 - Production/Stable
Classifier: Intended Audience :: End Users/Desktop
Classifier: License :: OSI Approved :: GNU General Public License v3 (GPLv3)
Classifier: Operating System :: OS Independent
Classifier: Programming Language :: C++
Classifier: Topic :: Multimedia :: Sound/Audio :: Sound Synthesis
Requires-Python: >=3.8
License-File: COPYING
